hermes/dots/__init__.py
hermes/dots/__version__.py
hermes/dots/oem/__init__.py
hermes/dots/oem/constants.py
hermes/dots/oem/handler.py
hermes/dots/oem/producer.py
hermes/dots/oem/stream.py
hermes/dots/oem/user_settings.py
pysio_hermes_dots-0.0.3.dist-info/licenses/LICENSE
pysio_hermes_dots-0.0.3.dist-info/METADATA
pysio_hermes_dots-0.0.3.dist-info/WHEEL
pysio_hermes_dots-0.0.3.dist-info/top_level.txt
pysio_hermes_dots-0.0.3.dist-info/RECORD
