Metadata-Version: 2.4
Name: pysio-hermes-dots
Version: 0.0.3
Summary: A Movella DOTs IMUs support module for HERMES
Author-email: Maxim Yudayev <maxim.yudayev@gmail.com>, "e-Media Research Lab @ KU Leuven" <emedia@kuleuven.be>
License-Expression: MIT
Project-URL: Homepage, https://yudayev.com/hermes
Project-URL: Documentation, https://yudayev.com/hermes
Project-URL: Repository, https://github.com/maximyudayev/hermes-dots.git
Project-URL: Issues, https://github.com/maximyudayev/hermes/issues
Project-URL: Changelog, https://github.com/maximyudayev/hermes-dots/blob/main/CHANGELOG.md
Keywords: embedded ai,wearables,sensors,imu,movella,streaming,realtime processing,physiology
Classifier: Programming Language :: Python :: 3
Classifier: Operating System :: OS Independent
Classifier: Development Status :: 4 - Beta
Classifier: Intended Audience :: Healthcare Industry
Classifier: Intended Audience :: Education
Classifier: Intended Audience :: Developers
Classifier: Intended Audience :: Science/Research
Classifier: Topic :: Scientific/Engineering
Classifier: Topic :: Scientific/Engineering :: Artificial Intelligence
Classifier: Topic :: Scientific/Engineering :: Medical Science Apps.
Classifier: Topic :: System :: Distributed Computing
Requires-Python: <3.11,>=3.7
License-File: LICENSE
Requires-Dist: pysio-hermes
Requires-Dist: numpy==1.26.*
Dynamic: license-file
